odoo/addons/sale_global_discount/README.rst
odoo/addons/sale_global_discount/__init__.py
odoo/addons/sale_global_discount/__manifest__.py
odoo/addons/sale_global_discount/hooks.py
odoo/addons/sale_global_discount/i18n/ca.po
odoo/addons/sale_global_discount/i18n/ca_ES.po
odoo/addons/sale_global_discount/i18n/es.po
odoo/addons/sale_global_discount/i18n/fr.po
odoo/addons/sale_global_discount/i18n/it.po
odoo/addons/sale_global_discount/i18n/pt.po
odoo/addons/sale_global_discount/i18n/sale_global_discount.pot
odoo/addons/sale_global_discount/models/__init__.py
odoo/addons/sale_global_discount/models/account_tax.py
odoo/addons/sale_global_discount/models/sale_order.py
odoo/addons/sale_global_discount/models/sale_order_line.py
odoo/addons/sale_global_discount/readme/CONFIGURE.md
odoo/addons/sale_global_discount/readme/CONTRIBUTORS.md
odoo/addons/sale_global_discount/readme/DESCRIPTION.md
odoo/addons/sale_global_discount/readme/ROADMAP.md
odoo/addons/sale_global_discount/readme/USAGE.md
odoo/addons/sale_global_discount/static/description/icon.png
odoo/addons/sale_global_discount/static/description/icon.svg
odoo/addons/sale_global_discount/static/description/index.html
odoo/addons/sale_global_discount/tests/__init__.py
odoo/addons/sale_global_discount/tests/test_account_tax.py
odoo/addons/sale_global_discount/tests/test_sale_global_discount.py
odoo/addons/sale_global_discount/views/report_sale_order.xml
odoo/addons/sale_global_discount/views/sale_order_views.xml
odoo_addon_sale_global_discount-18.0.1.0.0.4.dist-info/METADATA
odoo_addon_sale_global_discount-18.0.1.0.0.4.dist-info/WHEEL
odoo_addon_sale_global_discount-18.0.1.0.0.4.dist-info/top_level.txt
odoo_addon_sale_global_discount-18.0.1.0.0.4.dist-info/RECORD
